topyaz/__version__.py
topyaz-1.0.3.dist-info/METADATA
topyaz-1.0.3.dist-info/WHEEL
topyaz-1.0.3.dist-info/entry_points.txt
topyaz-1.0.3.dist-info/licenses/LICENSE
topyaz-1.0.3.dist-info/RECORD
